tinyCUCM/__init__.py
tinyCUCM/ccs_models.py
tinyCUCM/client.py
tinyCUCM/decorators.py
tinyCUCM/exceptions.py
tinyCUCM/logger.py
tinyCUCM/ris_models.py
tinyCUCM/settings.py
tinyCUCM/sql_models.py
tinyCUCM/sql_models_old.py
tinycucm-0.2.958.dist-info/licenses/LICENSE
tinycucm-0.2.958.dist-info/METADATA
tinycucm-0.2.958.dist-info/WHEEL
tinycucm-0.2.958.dist-info/top_level.txt
tinycucm-0.2.958.dist-info/RECORD
