Metadata-Version: 2.4
Name: tinyCUCM
Version: 0.2.958
Summary: Cisco Unified Call Manager AXL Methods Collection.
Author-email: Luarvick <lu.luarvick@gmail.com>
Project-URL: Homepage, https://github.com/luarvick/tinyCUCM
Project-URL: Issues, https://github.com/luarvick/tinyCUCM/issues
Classifier: Programming Language :: Python :: 3
Classifier: License :: OSI Approved :: MIT License
Classifier: Operating System :: OS Independent
Requires-Python: >=3.10
License-File: LICENSE
Requires-Dist: zeep==4.3.1
Requires-Dist: pydantic==2.10.6
Dynamic: license-file
